<annotation>
	<folder>testjpgs</folder>
	<filename>image_bright_185.jpg</filename>
	<path>C:\Users\mycom\Google 드라이브\test-paper-detector\detectron2\data\images_new\train\testjpgs\image_bright_185.jpg</path>
	<source>
		<database>Unknown</database>
	</source>
	<size>
		<width>842</width>
		<height>1191</height>
		<depth>3</depth>
	</size>
	<segmented>0</segmented>
	<object>
		<name>question</name>
		<pose>Unspecified</pose>
		<truncated>0</truncated>
		<difficult>0</difficult>
		<bndbox>
			<xmin>63</xmin>
			<ymin>268</ymin>
			<xmax>390</xmax>
			<ymax>348</ymax>
		</bndbox>
	</object>
	<object>
		<name>question</name>
		<pose>Unspecified</pose>
		<truncated>0</truncated>
		<difficult>0</difficult>
		<bndbox>
			<xmin>68</xmin>
			<ymin>571</ymin>
			<xmax>400</xmax>
			<ymax>671</ymax>
		</bndbox>
	</object>
	<object>
		<name>question</name>
		<pose>Unspecified</pose>
		<truncated>0</truncated>
		<difficult>0</difficult>
		<bndbox>
			<xmin>426</xmin>
			<ymin>224</ymin>
			<xmax>731</xmax>
			<ymax>309</ymax>
		</bndbox>
	</object>
	<object>
		<name>question</name>
		<pose>Unspecified</pose>
		<truncated>0</truncated>
		<difficult>0</difficult>
		<bndbox>
			<xmin>424</xmin>
			<ymin>573</ymin>
			<xmax>762</xmax>
			<ymax>796</ymax>
		</bndbox>
	</object>
</annotation>
