<annotation>
	<folder>cut_jpgs</folder>
	<filename>image_292.jpg</filename>
	<path>C:\Users\mycom\Google 드라이브\test-paper-detector\detectron2\data\images_choice\train\cut_jpgs\image_292.jpg</path>
	<source>
		<database>Unknown</database>
	</source>
	<size>
		<width>311</width>
		<height>155</height>
		<depth>1</depth>
	</size>
	<segmented>0</segmented>
	<object>
		<name>not-choice</name>
		<pose>Unspecified</pose>
		<truncated>0</truncated>
		<difficult>0</difficult>
		<bndbox>
			<xmin>83</xmin>
			<ymin>103</ymin>
			<xmax>95</xmax>
			<ymax>114</ymax>
		</bndbox>
	</object>
	<object>
		<name>not-choice</name>
		<pose>Unspecified</pose>
		<truncated>0</truncated>
		<difficult>0</difficult>
		<bndbox>
			<xmin>144</xmin>
			<ymin>103</ymin>
			<xmax>155</xmax>
			<ymax>114</ymax>
		</bndbox>
	</object>
	<object>
		<name>not-choice</name>
		<pose>Unspecified</pose>
		<truncated>0</truncated>
		<difficult>0</difficult>
		<bndbox>
			<xmin>204</xmin>
			<ymin>102</ymin>
			<xmax>216</xmax>
			<ymax>114</ymax>
		</bndbox>
	</object>
	<object>
		<name>not-choice</name>
		<pose>Unspecified</pose>
		<truncated>0</truncated>
		<difficult>0</difficult>
		<bndbox>
			<xmin>264</xmin>
			<ymin>103</ymin>
			<xmax>275</xmax>
			<ymax>114</ymax>
		</bndbox>
	</object>
	<object>
		<name>choice</name>
		<pose>Unspecified</pose>
		<truncated>0</truncated>
		<difficult>0</difficult>
		<bndbox>
			<xmin>22</xmin>
			<ymin>94</ymin>
			<xmax>36</xmax>
			<ymax>114</ymax>
		</bndbox>
	</object>
</annotation>
